edgedb_pydantic_codegen/__init__.py
edgedb_pydantic_codegen/__main__.py
edgedb_pydantic_codegen/generator.py
edgedb_pydantic_codegen/models.py
edgedb_pydantic_codegen/template.py.jinja
edgedb_pydantic_codegen/utils.py
edgedb_pydantic_codegen-2025.3.1.dist-info/METADATA
edgedb_pydantic_codegen-2025.3.1.dist-info/WHEEL
edgedb_pydantic_codegen-2025.3.1.dist-info/entry_points.txt
edgedb_pydantic_codegen-2025.3.1.dist-info/licenses/LICENSE
edgedb_pydantic_codegen-2025.3.1.dist-info/RECORD
