Metadata-Version: 2.4
Name: edgedb-pydantic-codegen
Version: 2025.3.1
Summary: Alternative Python EdgeDB code generator (Pydantic V2 + asyncio, FastAPI compatible)
Project-URL: homepage, https://github.com/Japan7/edgedb-pydantic-codegen
Author-email: NextFire <git@yuru.moe>
License-Expression: MIT
License-File: LICENSE
Requires-Python: >=3.11
Requires-Dist: edgedb<3,>=1
Requires-Dist: jinja2<4,>=3
Requires-Dist: orjson<4,>=3
Requires-Dist: pydantic<3,>=2
Requires-Dist: ruff<1,>=0.1.2
